yaps/__init__.py
yaps/decorator.py
yaps/ir.py
yaps/labeled_strings.py
yaps/lib.py
yaps/py2ir.py
yaps/roundtrip.py
yaps/stan2yaps.py
yaps/stanLexer.py
yaps/stanListener.py
yaps/stanParser.py
yaps/stanStats.py
yaps-0.1.4.dist-info/METADATA
yaps-0.1.4.dist-info/RECORD
yaps-0.1.4.dist-info/WHEEL
yaps-0.1.4.dist-info/entry_points.txt
yaps-0.1.4.dist-info/top_level.txt
