Metadata-Version: 2.1
Name: yaps
Version: 0.1.4
Summary: A surface language for programming Stan models using python syntax
Home-page: https://github.com/IBM/yaps
Author: Guillaume Baudart, Martin Hirzel, Kiran Kate, Louis Mandel, Avraham Shinnar
License: Apache License 2.0
Platform: UNKNOWN
Requires-Dist: astor
Requires-Dist: graphviz
Requires-Dist: antlr4-python3-runtime
Requires-Dist: pycmdstan
